optas/__init__.py
optas/builder.py
optas/models.py
optas/optimization.py
optas/solver.py
optas/spatialmath.py
optas/sx_container.py
optas/templates.py
optas/visualize.py
pyoptas-1.0.7.dist-info/LICENSE
pyoptas-1.0.7.dist-info/METADATA
pyoptas-1.0.7.dist-info/WHEEL
pyoptas-1.0.7.dist-info/top_level.txt
pyoptas-1.0.7.dist-info/RECORD
