Metadata-Version: 2.1
Name: pyoptas
Version: 1.0.7
Summary: An optimization-based task specification library for task and motion planning (TAMP), trajectory optimization, and model predictive control.
Home-page: https://github.com/cmower/optas
Author: Christopher E. Mower
Author-email: "Christopher E. Mower" <christopher.mower@kcl.ac.uk>
License: Apache License, Version 2.0
Project-URL: Homepage, https://cmower.github.io/optas/
Project-URL: Documentation, https://cmower.github.io/optas/
Project-URL: Bug Tracker, https://github.com/cmower/optas/issues
Project-URL: Source, https://github.com/cmower/optas
Classifier: Programming Language :: Python :: 3
Classifier: License :: OSI Approved :: Apache Software License
Classifier: Operating System :: OS Independent
Requires-Python: >=3.7
License-File: LICENSE
Requires-Dist: numpy
Requires-Dist: scipy
Requires-Dist: casadi
Requires-Dist: urdf-parser-py
Requires-Dist: osqp
Requires-Dist: cvxopt
Requires-Dist: xacro
Requires-Dist: vtk
Requires-Dist: pyyaml
Provides-Extra: example
Requires-Dist: pybullet ; extra == 'example'
Requires-Dist: matplotlib ; extra == 'example'
Provides-Extra: test
Requires-Dist: roboticstoolbox-python ; extra == 'test'
Requires-Dist: pybullet ; extra == 'test'
Requires-Dist: pytest ; extra == 'test'
Requires-Dist: matplotlib ; extra == 'test'
